Metadata-Version: 2.4
Name: dtale-cn
Version: 4.0.4
Summary: Web Client for Visualizing Pandas Objects
Home-page: https://www.dtale.cn
Author: WangLaoShi
Author-email: ginger547@gmail.com
License: LGPL
Keywords: numeric,pandas,visualization,flask
Classifier: Development Status :: 4 - Beta
Classifier: License :: OSI Approved :: GNU Library or Lesser General Public License (LGPL)
Classifier: Operating System :: OS Independent
Classifier: Intended Audience :: Science/Research
Classifier: Programming Language :: Python
Classifier: Programming Language :: Python :: 3.7
Classifier: Programming Language :: Python :: 3.8
Classifier: Programming Language :: Python :: 3.9
Classifier: Programming Language :: Python :: 3.10
Classifier: Programming Language :: Python :: 3.11
Requires-Python: >=3.7
License-File: LICENSE
Requires-Dist: lz4
Requires-Dist: beautifulsoup4
Requires-Dist: Brotli
Requires-Dist: certifi
Requires-Dist: cycler
Requires-Dist: dash!=2.13.0
Requires-Dist: dash-bootstrap-components<=1.7.1
Requires-Dist: dash_daq<=0.5.0
Requires-Dist: decorator
Requires-Dist: et_xmlfile
Requires-Dist: Flask
Requires-Dist: Flask-Compress
Requires-Dist: future>=0.14.0
Requires-Dist: itsdangerous
Requires-Dist: joblib
Requires-Dist: kaleido
Requires-Dist: kiwisolver
Requires-Dist: MarkupSafe
Requires-Dist: matplotlib
Requires-Dist: missingno
Requires-Dist: networkx
Requires-Dist: numpy
Requires-Dist: openpyxl
Requires-Dist: packaging
Requires-Dist: pandas
Requires-Dist: plotly
Requires-Dist: pyparsing
Requires-Dist: requests
Requires-Dist: scikit-learn
Requires-Dist: scipy
Requires-Dist: seaborn
Requires-Dist: squarify
Requires-Dist: statsmodels
Requires-Dist: strsimpy
Requires-Dist: six
Requires-Dist: tenacity
Requires-Dist: threadpoolctl
Requires-Dist: urllib3
Requires-Dist: werkzeug
Requires-Dist: xarray
Requires-Dist: xlrd
Requires-Dist: zipp
Requires-Dist: zstandard
Provides-Extra: arctic
Requires-Dist: arctic<=1.79.4; extra == "arctic"
Provides-Extra: arcticdb
Requires-Dist: arcticdb; extra == "arcticdb"
Provides-Extra: dash-bio
Requires-Dist: ParmEd==3.4.3; python_version == "3.6" and extra == "dash-bio"
Requires-Dist: dash-bio; python_version > "3.0" and extra == "dash-bio"
Provides-Extra: ngrok
Requires-Dist: flask-ngrok; python_version > "3.0" and extra == "ngrok"
Provides-Extra: r
Requires-Dist: rpy2; python_version > "3.0" and extra == "r"
Provides-Extra: redis
Requires-Dist: redis; extra == "redis"
Requires-Dist: redislite; extra == "redis"
Provides-Extra: streamlit
Requires-Dist: streamlit; extra == "streamlit"
Provides-Extra: swifter
Requires-Dist: swifter; extra == "swifter"
Provides-Extra: tests
Requires-Dist: pytest; extra == "tests"
Requires-Dist: pytest-cov; extra == "tests"
Requires-Dist: tox; extra == "tests"
Requires-Dist: flake8; extra == "tests"
Dynamic: license-file
